{"title":"Combined feed","url":"https://KPOPCORD.github.io/community/all.xml","elements":[{"title":"[연예] [스테이씨] 1년만에 흑자전환을 앞둔 중소 걸그룹?.youtube (Pgr21 ─ 연예)","contents":"Bar Sur","link":"https://ppt21.com/spoent/63693?category=2","retrieved":1634311398146},{"title":"[연예] MC스나이퍼 근황 (Pgr21 ─ 연예)","contents":"TWICE쯔위","link":"https://ppt21.com/spoent/63691?category=2","retrieved":1634307638485},{"title":"[연예] [트와이스] 쉴 틈이 없다! 데뷔 6주년 타임테이블 공개 (Pgr21 ─ 연예)","contents":"Davi4ever","link":"https://ppt21.com/spoent/63690?category=2","retrieved":1634304384252},{"title":"[연예] 타짜 곽철용선생에게 고스톱 배우는 효짱과 입커누나 (Pgr21 ─ 연예)","contents":"강가딘","link":"https://ppt21.com/spoent/63689?category=2","retrieved":1634301294560},{"title":"[연예] 김세정 - 아이와 나의 바다 (IU) 커버 CLEAN_ver 100만 뷰 달성 (Pgr21 ─ 연예)","contents":"자두삶아","link":"https://ppt21.com/spoent/63687?category=2","retrieved":1634301294562},{"title":"[연예] 넷플릭스 [마이 네임] 1화 본 느낌...(스포 없음) (Pgr21 ─ 연예)","contents":"우주전쟁","link":"https://ppt21.com/spoent/63686?category=2","retrieved":1634296807574},{"title":"[연예] 10월 14일부로 중국 아이돌 앨범 공구 무기한 중단 (Pgr21 ─ 연예)","contents":"TWICE쯔위","link":"https://ppt21.com/spoent/63685?category=2","retrieved":1634296807579},{"title":"[연예] e-스포츠 아나운서 3인의 고스톱 한판 (Pgr21 ─ 연예)","contents":"강가딘","link":"https://ppt21.com/spoent/63684?category=2","retrieved":1634289690698},{"title":"[연예] [에스파] 오늘 뮤직뱅크 1위 후보 상황 (Pgr21 ─ 연예)","contents":"Bronx Bombers","link":"https://ppt21.com/spoent/63681?category=2","retrieved":1634286373458},{"title":"[연예] [에스파] 경멸의 눈빛 (Pgr21 ─ 연예)","contents":"바스테나","link":"https://ppt21.com/spoent/63679?category=2","retrieved":1634282570357},{"title":"[연예] 휘파람으로 오징어게임 OST 재현하는 이종범 웹툰작가 (Pgr21 ─ 연예)","contents":"강가딘","link":"https://ppt21.com/spoent/63678?category=2","retrieved":1634279198919},{"title":"[연예] [트와이스] \"The Feels\" M/V 비하인드 영상 EP1~EP3 (Pgr21 ─ 연예)","contents":"Davi4ever","link":"https://ppt21.com/spoent/63676?category=2","retrieved":1634272151274},{"title":"[연예] 오징어 게임 넷플릭스 랭킹 현황... (Pgr21 ─ 연예)","contents":"우주전쟁","link":"https://ppt21.com/spoent/63672?category=2","retrieved":1634253739204},{"title":"[연예] 오늘 있었던 \"디즈니플러스\" 한국 쇼케이스에 참석한 배우들 (Pgr21 ─ 연예)","contents":"아롱이다롱이","link":"https://ppt21.com/spoent/63670?category=2","retrieved":1634224999947},{"title":"[연예] [골목식당] 콩나물국밥 맛집 (Pgr21 ─ 연예)","contents":"Croove","link":"https://ppt21.com/spoent/63669?category=2","retrieved":1634224999947},{"title":"[연예] 큐브 라잇썸 엠카 \"VIVACE\" 첫 컴백무대 공개 (Pgr21 ─ 연예)","contents":"초원을달리다","link":"https://ppt21.com/spoent/63668?category=2","retrieved":1634217968975},{"title":"[연예] [에스파] 엠카운트다운 컴백무대 영상 (+직캠) (Pgr21 ─ 연예)","contents":"Davi4ever","link":"https://ppt21.com/spoent/63667?category=2","retrieved":1634210321178},{"title":"[연예] 바람의검심 더비기닝 발도재 vs 오키타 (Pgr21 ─ 연예)","contents":"Croove","link":"https://ppt21.com/spoent/63666?category=2","retrieved":1634210321178},{"title":"[연예] 영화 <듄> 시사 초반 트위터 반응 (Pgr21 ─ 연예)","contents":"빼사스","link":"https://ppt21.com/spoent/63665?category=2","retrieved":1634207068099}]}