{"title":"Pgr21 ─ 연예","url":"https://ppt21.com/spoent/0?1=1&category=2","favicon":"https://ppt21.com/spoent/favicon.ico","elements":[{"title":"[연예] TV광고로 선공개 된 태연 3집 타이틀곡","contents":"KIMTAEYEON","link":"https://ppt21.com/spoent/66126?category=2","retrieved":1644642832242},{"title":"[연예] 뷔페에 간 유민상.swf","contents":"TWICE쯔위","link":"https://ppt21.com/spoent/66125?category=2","retrieved":1644642832242},{"title":"[연예] 초딩/중딩한태 DM 엄청 받는다는 김동현","contents":"강가딘","link":"https://ppt21.com/spoent/66124?category=2","retrieved":1644635732136},{"title":"[연예] 다음주 유퀴즈에 나오는 [그해 우리는]의 원작 EBS 1등과 꼴찌","contents":"빼사스","link":"https://ppt21.com/spoent/66121?category=2","retrieved":1644592556510},{"title":"[연예] [에이핑크] 'Dilemma' M/V Teaser #1","contents":"Davi4ever","link":"https://ppt21.com/spoent/66119?category=2","retrieved":1644592556511},{"title":"[연예] [NMIXX] 첫 싱글 <AD MARE> 콘셉트 포토 'N' (릴리, 지우, 규진)","contents":"Davi4ever","link":"https://ppt21.com/spoent/66112?category=2","retrieved":1644556461656},{"title":"[연예] 완전체로 컴백하는 에픽하이 '그래서 그래' 티저.ytb","contents":"VictoryFood","link":"https://ppt21.com/spoent/66103?category=2","retrieved":1644510173133},{"title":"[연예] 최예나, 엠카에서 솔로데뷔 후 첫 음방 1위 (+앵콜 직캠)","contents":"Davi4ever","link":"https://ppt21.com/spoent/66101?category=2","retrieved":1644499116692},{"title":"[연예] [VIVIZ] 엠카운트다운 음방 데뷔 무대 (+직캠 영상)","contents":"Davi4ever","link":"https://ppt21.com/spoent/66100?category=2","retrieved":1644499116692},{"title":"[연예] 현빈 - 손예진 커플 결혼","contents":"나의 연인","link":"https://ppt21.com/spoent/66098?category=2","retrieved":1644495989203},{"title":"[연예] 야구선수 황재균 - 티아라 지연 결혼","contents":"껌정","link":"https://ppt21.com/spoent/66096?category=2","retrieved":1644491598125},{"title":"[연예] 김종국·양세찬 확진-지석진 키트 양성","contents":"반니스텔루이","link":"https://ppt21.com/spoent/66095?category=2","retrieved":1644491598130},{"title":"[연예] [엠카]NEXT WEEK  태연,에이핑크","contents":"KIMTAEYEON","link":"https://ppt21.com/spoent/66093?category=2","retrieved":1644491598130},{"title":"[연예] 태연 'INVU' Clip #2, #3 , 티저 이미지","contents":"KIMTAEYEON","link":"https://ppt21.com/spoent/66092?category=2","retrieved":1644488250681},{"title":"[연예] 66080글의 영상버전 - 유퀴즈 대타MC 침착맨","contents":"A1","link":"https://ppt21.com/spoent/66091?category=2","retrieved":1644477297279},{"title":"[연예] [NMIXX] 첫 싱글 <AD MARE> 콘셉트 포토 'N' (지니, 배이)","contents":"Davi4ever","link":"https://ppt21.com/spoent/66085?category=2","retrieved":1644423829426},{"title":"[연예] 유퀴즈 조세호 대타","contents":"껌정","link":"https://ppt21.com/spoent/66080?category=2","retrieved":1644416073243},{"title":"[연예] [비비지] - 'BOP BOP!' MV","contents":"VictoryFood","link":"https://ppt21.com/spoent/66075?category=2","retrieved":1644401837998},{"title":"[연예] 취소 후 다시 살아 돌아온 태연 하라클#1","contents":"KIMTAEYEON","link":"https://ppt21.com/spoent/66074?category=2","retrieved":1644401837999}]}