{"title":"Pgr21 ─ 연예","url":"https://ppt21.com/spoent/0?1=1&category=2","favicon":"https://ppt21.com/spoent/favicon.ico","elements":[{"title":"[연예] VIVIZ 2022 시즌그리팅 비하인드 신","contents":"김캇트","link":"https://ppt21.com/spoent/65512?category=2","retrieved":1641827891353},{"title":"[연예] [에스파] 'Dreams Come True' 인기가요 페이스캠 (+음중 직캠)","contents":"Davi4ever","link":"https://ppt21.com/spoent/65509?category=2","retrieved":1641817662309},{"title":"[연예] [러블리즈][쟤와 벌] 1화 - Q&A, 밸런스게임","contents":"유지애","link":"https://ppt21.com/spoent/65506?category=2","retrieved":1641809960289},{"title":"[연예] 요즘 음악방송 카메라무빙.gif","contents":"이히리기우구추","link":"https://ppt21.com/spoent/65505?category=2","retrieved":1641806282789},{"title":"[연예] 2021년 1월 2주 D-차트 : 아이브 3주째 1위! 아이유는 3위 진입","contents":"Davi4ever","link":"https://ppt21.com/spoent/65503?category=2","retrieved":1641802891528},{"title":"[연예] 넷플릭스 월드랭킹 TOP10에 위치한 유일한 한국프로","contents":"인사이더","link":"https://ppt21.com/spoent/65502?category=2","retrieved":1641802891534},{"title":"[연예] <민희진 걸그룹, 사쿠라 걸그룹, 걸그룹 오디션> 하이브 걸그룹 3팀 데뷔","contents":"아롱이다롱이","link":"https://ppt21.com/spoent/65500?category=2","retrieved":1641788543915},{"title":"[연예] ‘오징어게임’ 오영수, 한국배우 최초 美 골든글로브 조연상 수상…이정재 주연상 불발","contents":"강가딘","link":"https://ppt21.com/spoent/65499?category=2","retrieved":1641784729207},{"title":"[연예] 2월 데뷔, jyp 7인조 신인걸그룹 멤버들","contents":"아롱이다롱이","link":"https://ppt21.com/spoent/65495?category=2","retrieved":1641759511019},{"title":"[연예] [태종이방원]이방원과 강씨의 말싸움","contents":"카루오스","link":"https://ppt21.com/spoent/65493?category=2","retrieved":1641745532930},{"title":"[연예] (이방원) 슬슬 다들 기대하는 장면","contents":"길갈","link":"https://ppt21.com/spoent/65492?category=2","retrieved":1641741413500},{"title":"[연예] [에버글로우] 왕이런 중국으로 일시 귀국","contents":"Bronx Bombers","link":"https://ppt21.com/spoent/65486?category=2","retrieved":1641731184778},{"title":"[연예] 아이브, 오늘자 인기가요 1위 7관왕","contents":"아롱이다롱이","link":"https://ppt21.com/spoent/65485?category=2","retrieved":1641731184786},{"title":"[연예] 다이아 솜이 근황","contents":"이히리기우구추","link":"https://ppt21.com/spoent/65482?category=2","retrieved":1641712573903},{"title":"[연예] 개승자 후반전","contents":"빼사스","link":"https://ppt21.com/spoent/65481?category=2","retrieved":1641705427852},{"title":"[연예] 2021년 12월 여자가수 음반판매량(가온기준)","contents":"VictoryFood","link":"https://ppt21.com/spoent/65479?category=2","retrieved":1641702148358},{"title":"[연예] 존잘남의 학창시절 인기.JPG","contents":"insane","link":"https://ppt21.com/spoent/65478?category=2","retrieved":1641698389718},{"title":"[연예] [AEW]현재 미국 프로레슬링에서 가장 재밌는 대립","contents":"kien.","link":"https://ppt21.com/spoent/65477?category=2","retrieved":1641694466994},{"title":"[연예] [아이브] 음악중심 1위와 함께 어느덧 6관왕","contents":"Davi4ever","link":"https://ppt21.com/spoent/65474?category=2","retrieved":1641655027817}]}