{"title":"Pgr21 ─ 연예","url":"https://ppt21.com/spoent/0?1=1&category=2","favicon":"https://ppt21.com/spoent/favicon.ico","elements":[{"title":"[연예] [아이유] 드디어 중단발로 자른 아이유.insta + 꿈빛파티시엘 챌린지","contents":"VictoryFood","link":"https://ppt21.com/spoent/64585?category=2","retrieved":1637918707141},{"title":"[연예] 자우림 정규11집 타이틀곡 'STAY WITH ME' M/V","contents":"Davi4ever","link":"https://ppt21.com/spoent/64584?category=2","retrieved":1637918707141},{"title":"[연예] OTT 작품, 청룡영화상 최초 노미네이트 \"경계 넘어 더 넓은 곳으로\"","contents":"강가딘","link":"https://ppt21.com/spoent/64583?category=2","retrieved":1637915228344},{"title":"[연예] BTS 공연 보려고 먼 길을 떠나는 아미...","contents":"우주전쟁","link":"https://ppt21.com/spoent/64581?category=2","retrieved":1637915228351},{"title":"[연예] 고요의 바다 티저","contents":"어강됴리","link":"https://ppt21.com/spoent/64576?category=2","retrieved":1637888980737},{"title":"[연예] 25일자 넷플릭스 월드랭킹 top10 정리","contents":"아롱이다롱이","link":"https://ppt21.com/spoent/64575?category=2","retrieved":1637878960485},{"title":"[연예] [JYPN] Survivor Cover | QUALIFYING (릴리 해원)","contents":"TWICE쯔위","link":"https://ppt21.com/spoent/64572?category=2","retrieved":1637853891329},{"title":"[연예] 음악중심 야외무대 레전드들","contents":"한국화약주식회사","link":"https://ppt21.com/spoent/64571?category=2","retrieved":1637853891329},{"title":"[연예] 아이브 IVE THE 1st SINGLE ALBUM <ELEVEN> CONCEPT PHOTO 단체사진","contents":"아롱이다롱이","link":"https://ppt21.com/spoent/64570?category=2","retrieved":1637853891329},{"title":"[연예] Tokopedia 인도네시아 케이팝 어워드 걸그룹 무대 모음","contents":"발적화","link":"https://ppt21.com/spoent/64569?category=2","retrieved":1637853891329},{"title":"[연예] 일반인 가요제 무대 레전드","contents":"나스닥","link":"https://ppt21.com/spoent/64567?category=2","retrieved":1637846862488},{"title":"[연예] 자, 한 달 후면 공개다...","contents":"우주전쟁","link":"https://ppt21.com/spoent/64563?category=2","retrieved":1637821673071},{"title":"[연예] 키 170cm 몸무게 46kg 이라는 ITZY 유나","contents":"Anti-MAGE","link":"https://ppt21.com/spoent/64560?category=2","retrieved":1637807783539},{"title":"[연예] 미스터트롯 결승전에 포경수술 하고 종이컵 차고 노래부른 가수.jpg","contents":"insane","link":"https://ppt21.com/spoent/64557?category=2","retrieved":1637807783542},{"title":"[연예] Ed Sheeran - Shivers (feat. Jessi, SUNMI)","contents":"어강됴리","link":"https://ppt21.com/spoent/64556?category=2","retrieved":1637802759743},{"title":"[연예] 이 형님들 아직도 활동하고 계셨네요...","contents":"우주전쟁","link":"https://ppt21.com/spoent/64555?category=2","retrieved":1637802759744},{"title":"[연예] 24일자 넷플릭스 월드랭킹 top10 정리","contents":"아롱이다롱이","link":"https://ppt21.com/spoent/64554?category=2","retrieved":1637788769082},{"title":"[연예] 대낮에 LA 도로 점거하는 한국의 청년들","contents":"style","link":"https://ppt21.com/spoent/64553?category=2","retrieved":1637767496714},{"title":"[연예] 아이브 IVE THE 1st SINGLE ALBUM <ELEVEN> CONCEPT PHOTO  리즈 / 이서","contents":"아롱이다롱이","link":"https://ppt21.com/spoent/64552?category=2","retrieved":1637763677207}]}